jinja2_error/__init__.py
jinja2_error/jinja2_error.py
jinja2_error-0.1.0.dist-info/METADATA
jinja2_error-0.1.0.dist-info/WHEEL
jinja2_error-0.1.0.dist-info/top_level.txt
jinja2_error-0.1.0.dist-info/RECORD
