Metadata-Version: 2.1
Name: jinja2-error
Version: 0.1.0
Summary: Jinja2 Extension for Raise Error
Home-page: https://github.com/mumubin/jiaja2_error
Author: Robin Hu
Author-email: given.hubin@gmail.com
Maintainer: Robin Hu
Maintainer-email: given.hubin@gmail.com
License: MIT
Keywords: jinja2,extension,error
Platform: UNKNOWN
Classifier: Development Status :: 3 - Alpha
Classifier: Intended Audience :: Developers
Classifier: License :: OSI Approved :: MIT License
Classifier: Natural Language :: English
Classifier: Operating System :: OS Independent
Classifier: Programming Language :: Python :: 2
Classifier: Programming Language :: Python :: 2.7
Classifier: Programming Language :: Python :: 3
Classifier: Programming Language :: Python :: 3.3
Classifier: Programming Language :: Python :: 3.4
Classifier: Programming Language :: Python :: 3.5
Classifier: Programming Language :: Python :: Implementation :: CPython
Classifier: Programming Language :: Python :: Implementation :: PyPy
Classifier: Programming Language :: Python
Requires-Dist: jinja2
Requires-Dist: arrow (<=0.13.2) ; python_version<='3.4'
Requires-Dist: arrow ; python_version=='2.7'
Requires-Dist: arrow ; python_version>='3.5'
